{
  "builds": [
    {
      "date": "2026-01-06T06:10:33.669Z",
      "themeName": "Dawn Manuscript",
      "status": "success",
      "colors": {
        "light": "#FDF2E9",
        "dark": "#1C1410"
      },
      "fonts": {
        "heading": "Playfair Display",
        "body": "Source Serif 4"
      },
      "navStyle": "minimal",
      "cardStyle": "flat",
      "heroLayout": "left-aligned",
      "linkStyle": "underline",
      "texture": "grain",
      "imageStyle": "muted",
      "imageHover": "lift"
    },
    {
      "date": "2026-01-05T17:04:24.442Z",
      "themeName": "Morning Hearth",
      "status": "success",
      "colors": {
        "light": "#FFF5E6",
        "dark": "#1A0F0A"
      },
      "fonts": {
        "heading": "Fraunces",
        "body": "Inter"
      },
      "navStyle": "floating",
      "cardStyle": "glass",
      "heroLayout": "left-aligned",
      "linkStyle": "highlight",
      "texture": "grain",
      "imageStyle": "vivid",
      "imageHover": "lift"
    },
    {
      "date": "2026-01-04T20:03:20.120Z",
      "themeName": "Precision Grid",
      "status": "success",
      "colors": {
        "light": "#FDEBD0",
        "dark": "#1C1410"
      },
      "fonts": {
        "heading": "Space Grotesk",
        "body": "Inter"
      },
      "navStyle": "bold-bar",
      "cardStyle": "flat",
      "heroLayout": "bold",
      "linkStyle": "bracket",
      "texture": "grid",
      "imageStyle": "vivid",
      "imageHover": "lift"
    },
    {
      "date": "2026-01-04T20:03:01.639Z",
      "themeName": "Golden Metropolis",
      "status": "success",
      "colors": {
        "light": "#FDF2E9",
        "dark": "#1A0F0A"
      },
      "fonts": {
        "heading": "Bodoni Moda",
        "body": "Inter"
      },
      "navStyle": "bold-bar",
      "cardStyle": "outlined",
      "heroLayout": "bold",
      "linkStyle": "bracket",
      "texture": "grid",
      "imageStyle": "duotone",
      "imageHover": "glow"
    },
    {
      "date": "2026-01-04T16:40:41.825Z",
      "themeName": "Midnight Bazaar",
      "status": "success",
      "colors": {
        "light": "#F4ECF7",
        "dark": "#2D132C"
      },
      "fonts": {
        "heading": "Syne",
        "body": "IBM Plex Sans"
      },
      "navStyle": "floating",
      "cardStyle": "glass",
      "heroLayout": "left-aligned",
      "linkStyle": "highlight",
      "texture": "dots",
      "imageStyle": "duotone",
      "imageHover": "glow"
    },
    {
      "date": "2026-01-04T15:28:58.296Z",
      "themeName": "Sunday Study",
      "status": "success",
      "colors": {
        "light": "#FDF2E9",
        "dark": "#1C1410"
      },
      "fonts": {
        "heading": "Cormorant Garamond",
        "body": "Source Serif 4"
      },
      "navStyle": "minimal",
      "cardStyle": "elevated"
    },
    {
      "date": "2026-01-04T06:35:32.260Z",
      "themeName": "Arctic Oracle",
      "status": "success",
      "colors": {
        "light": "#E8F6F3",
        "dark": "#0D1F22"
      },
      "font": "Cormorant Garamond"
    },
    {
      "date": "2026-01-04T06:12:50.664Z",
      "themeName": "Electric Mint",
      "status": "success",
      "colors": {
        "light": "#f0fdf4",
        "dark": "#0f1f0f"
      },
      "font": "Space Grotesk"
    },
    {
      "date": "2026-01-04T06:04:39.007Z",
      "themeName": "Electric Sunset",
      "status": "success",
      "colors": {
        "light": "#fff5f0",
        "dark": "#1a0f0a"
      },
      "font": "Space Grotesk"
    },
    {
      "date": "2026-01-04T05:57:59.108Z",
      "themeName": "Electric Mint",
      "status": "success",
      "colors": {
        "light": "#f0fdf9",
        "dark": "#0c1f1a"
      },
      "font": "Space Grotesk"
    },
    {
      "date": "2026-01-04T05:49:42.612Z",
      "themeName": "Winter Manuscript",
      "status": "success",
      "colors": {
        "light": "#f7fafc",
        "dark": "#1a202c"
      },
      "font": "Cormorant Garamond"
    }
  ]
}